ocelot/__init__.py
ocelot/constants.py
ocelot/core.py
ocelot/pseudopotential.py
ocelot/visualizations.py
ocelot/wavefunction.py
ocelot_materials-0.0.6.dist-info/LICENSE.txt
ocelot_materials-0.0.6.dist-info/METADATA
ocelot_materials-0.0.6.dist-info/WHEEL
ocelot_materials-0.0.6.dist-info/top_level.txt
ocelot_materials-0.0.6.dist-info/RECORD
