Metadata-Version: 2.1
Name: ocelot-materials
Version: 0.0.6
Summary: (Under development). Ocelot is a framework for materials simulations.
Home-page: https://ocelotmaterials.com
Author: Leandro Seixas
Author-email: contact@ocelotmaterials.com
License: Apache 2
Platform: UNKNOWN
Classifier: Development Status :: 1 - Planning
Classifier: Programming Language :: Python :: 3
Classifier: Topic :: Scientific/Engineering :: Chemistry
Classifier: Topic :: Scientific/Engineering :: Physics
Classifier: License :: OSI Approved :: Apache Software License
Classifier: Operating System :: OS Independent
Requires-Python: >= 3.5.*
Requires-Dist: numpy (>=1.*)
Requires-Dist: pandas (>=0.24.*)
Requires-Dist: scipy (>=1.*)
